demo/cli.py
demo_cli-1.0.4.dist-info/licenses/LICENSE
demo_cli-1.0.4.dist-info/METADATA
demo_cli-1.0.4.dist-info/WHEEL
demo_cli-1.0.4.dist-info/entry_points.txt
demo_cli-1.0.4.dist-info/top_level.txt
demo_cli-1.0.4.dist-info/RECORD
