Metadata-Version: 2.4
Name: demo-cli
Version: 1.0.4
Summary: EZDEMO makes it easy to demo your web app.
Author-email: Q2k <q2k@q2k.dev>
License: MIT
Project-URL: Source, https://github.com/q2kit/demo
Requires-Python: >=3.7
License-File: LICENSE
Requires-Dist: paramiko>=2.11.0
Requires-Dist: requests>=2.25.0
Dynamic: license-file
